{
  "id": "9231157",
  "name": "تسنيم محمد ابراهيم عبد المعطي الطنباري",
  "semester": "Final - Spring",
  "academicYear": "2026/2027",
  "exams": [
    {
      "courseCode": "MLA324",
      "courseName": "Histopathology and Cytology",
      "examStartISO": "2026-07-21T11:45:00+03:00",
      "examEndISO": "2026-07-21T13:45:00+03:00",
      "detailsAvailable": false,
      "countdownHours": 65.61,
      "location": "Hall (3) Building 8",
      "seat": "35",
      "room": null,
      "building": null
    },
    {
      "courseCode": "MLA322",
      "courseName": "Clinical Chemistry 2",
      "examStartISO": "2026-07-23T11:45:00+03:00",
      "examEndISO": "2026-07-23T13:45:00+03:00",
      "detailsAvailable": false,
      "countdownHours": 113.61,
      "location": "Hall (3) Building 8",
      "seat": "62",
      "room": null,
      "building": null
    },
    {
      "courseCode": "MLA321",
      "courseName": "Hematology (2)",
      "examStartISO": "2026-07-31T09:30:00+03:00",
      "examEndISO": "2026-07-31T11:30:00+03:00",
      "detailsAvailable": false,
      "countdownHours": 303.36,
      "location": "Hall (5) Building 8",
      "seat": "16",
      "room": null,
      "building": null
    },
    {
      "courseCode": "MLA312E",
      "courseName": "Health Education",
      "examStartISO": "2026-08-06T09:30:00+03:00",
      "examEndISO": "2026-08-06T11:30:00+03:00",
      "detailsAvailable": false,
      "countdownHours": 447.36,
      "location": "Hall (3) Building 8",
      "seat": "25",
      "room": null,
      "building": null
    },
    {
      "courseCode": "MLA323",
      "courseName": "Virology &Mycology",
      "examStartISO": "2026-08-08T11:45:00+03:00",
      "examEndISO": "2026-08-08T13:45:00+03:00",
      "detailsAvailable": false,
      "countdownHours": 497.61,
      "location": "Hall (5) Building 8",
      "seat": "5",
      "room": null,
      "building": null
    }
  ],
  "nextExam": {
    "courseCode": "MLA324",
    "courseName": "Histopathology and Cytology",
    "examStartISO": "2026-07-21T11:45:00+03:00",
    "examEndISO": "2026-07-21T13:45:00+03:00",
    "location": "Hall (3) Building 8",
    "seat": "35",
    "room": null,
    "building": null,
    "detailsAvailable": false,
    "countdownHours": 65.61
  }
}