{
  "id": "9231376",
  "name": "شهد على محمد على",
  "semester": "Final - Spring",
  "academicYear": "2025/2026",
  "exams": [
    {
      "courseCode": "AHS124",
      "courseName": "Pharmacology for health science Technologists",
      "examStartISO": "2026-05-17T09:30:00+03:00",
      "examEndISO": "2026-05-17T11:30:00+03:00",
      "detailsAvailable": false,
      "countdownHours": 16.15,
      "location": "HALL (1) Building 8",
      "seat": "7",
      "room": null,
      "building": null
    },
    {
      "courseCode": "MLA224",
      "courseName": "Automation in Clinical Laboratories",
      "examStartISO": "2026-05-19T11:45:00+03:00",
      "examEndISO": "2026-05-19T13:45:00+03:00",
      "detailsAvailable": false,
      "countdownHours": 66.4,
      "location": "Classroom 9 (422,423) - Building 8 (كلية تكنولوجيا العلوم الصحية التطبيقية)",
      "seat": "4",
      "room": null,
      "building": null
    },
    {
      "courseCode": "GEN401",
      "courseName": "Marketing skills",
      "examStartISO": "2026-05-31T11:45:00+03:00",
      "examEndISO": "2026-05-31T12:30:00+03:00",
      "detailsAvailable": false,
      "countdownHours": 354.4,
      "location": "Computer lab 9 (307) (كلية الذكاء الاصطناعي)",
      "seat": "6",
      "room": null,
      "building": null
    },
    {
      "courseCode": "MLA223",
      "courseName": "Applied Microbiology",
      "examStartISO": "2026-06-15T09:30:00+03:00",
      "examEndISO": "2026-06-15T11:30:00+03:00",
      "detailsAvailable": false,
      "countdownHours": 712.15,
      "location": "HALL (3) Building 8",
      "seat": "12",
      "room": null,
      "building": null
    }
  ],
  "nextExam": {
    "courseCode": "AHS124",
    "courseName": "Pharmacology for health science Technologists",
    "examStartISO": "2026-05-17T09:30:00+03:00",
    "examEndISO": "2026-05-17T11:30:00+03:00",
    "location": "HALL (1) Building 8",
    "seat": "7",
    "room": null,
    "building": null,
    "detailsAvailable": false,
    "countdownHours": 16.15
  }
}